stress_tool/__init__.py
stress_tool/stress_tool.py
stress_tool-1.2.1.dist-info/METADATA
stress_tool-1.2.1.dist-info/WHEEL
stress_tool-1.2.1.dist-info/licenses/LICENSE
stress_tool-1.2.1.dist-info/RECORD
