Metadata-Version: 2.4
Name: stress_tool
Version: 1.2.1
Summary: Stress test tool with statistical TPS reports based on Worker Dispatcher in Python
Project-URL: Homepage, https://github.com/yidas/python-stress-tool
Project-URL: Issues, https://github.com/yidas/python-stress-tool/issues
Author-email: Nick Tsai <myintaer@gmail.com>
License-File: LICENSE
Classifier: License :: OSI Approved :: MIT License
Classifier: Operating System :: OS Independent
Classifier: Programming Language :: Python :: 3
Requires-Python: >=3.0
Requires-Dist: openpyxl>=3.0.0
Requires-Dist: worker-dispatcher>=1.3.1
